flask_hotline/__init__.py
flask_hotline-0.1.0.dist-info/METADATA
flask_hotline-0.1.0.dist-info/WHEEL
flask_hotline-0.1.0.dist-info/RECORD
