Metadata-Version: 2.4
Name: flask-hotline
Version: 0.1.0
Summary: Reactive Jinja2 components for your Flask Application.
Author: Drew Butcher
Author-email: drewlbutcher@gmail.com
Requires-Python: >=3.10
Classifier: Programming Language :: Python :: 3
Classifier: Programming Language :: Python :: 3.10
Classifier: Programming Language :: Python :: 3.11
Classifier: Programming Language :: Python :: 3.12
Classifier: Programming Language :: Python :: 3.13
Classifier: Programming Language :: Python :: 3.14
Requires-Dist: flask (>=3.0)
Requires-Dist: jinja2 (>=3.1)
Project-URL: Issues, https://github.com/drewbutcher/flask-hotline/issues
Project-URL: Repository, https://github.com/drewbutcher/flask-hotline
